palindrome_tree/__init__.py
palindrome_tree/model/palindrome-xgboost-tree.json
palindrome_tree/models.py
palindrome_tree/palindrome_tree.py
palindrome_tree-1.3.1.dist-info/LICENSE
palindrome_tree-1.3.1.dist-info/WHEEL
palindrome_tree-1.3.1.dist-info/METADATA
palindrome_tree-1.3.1.dist-info/RECORD
