Metadata-Version: 2.1
Name: palindrome-tree
Version: 1.3.1
Summary: Gradient boosted decision tree palindrome predictor, used to locate regions for further investigation thru http://palindromes.ibp.cz/
Home-page: https://github.com/patrikkaura/palindrome-tree
License: MIT
Keywords: DNA,palindrome
Author: jaromir.kratochvil
Author-email: 171433@vutbr.cz
Requires-Python: >=3.7.1,<4.0.0
Classifier: Intended Audience :: Education
Classifier: Intended Audience :: Science/Research
Classifier: License :: OSI Approved :: MIT License
Classifier: Operating System :: OS Independent
Classifier: Programming Language :: Python
Classifier: Programming Language :: Python :: 3
Classifier: Programming Language :: Python :: 3.7
Classifier: Programming Language :: Python :: 3.8
Classifier: Programming Language :: Python :: 3.9
Classifier: Topic :: Scientific/Engineering :: Artificial Intelligence
Classifier: Topic :: Scientific/Engineering :: Bio-Informatics
Requires-Dist: pandas (>=1.3.5,<2.0.0)
Requires-Dist: requests (>=2.26.0,<3.0.0)
Requires-Dist: scikit-learn (>=1.0.2,<2.0.0)
Requires-Dist: xgboost (>=1.5.1,<2.0.0)
Project-URL: Repository, https://github.com/patrikkaura/palindrome-tree
